{"content":[{"data":{"color":"black","source":"The Narrator","time_period":["0s AD"],"unique_sources":["John the Disciple"]},"nodes":[{"type":"prose","nodes":[{"marks":[{"data":{"book":"Joh","chapter":"20","verse":"1"},"object":"mark","type":"reference"}],"object":"leaf","text":"\t"},{"marks":[{"data":{"book":"Joh","chapter":"20","verse":"1"},"object":"mark","type":"reference"},{"object":"mark","type":"chapter"}],"object":"leaf","text":"20"},{"marks":[{"data":{"book":"Joh","chapter":"20","verse":"1"},"object":"mark","type":"reference"},{"object":"mark","type":"verse"}],"object":"leaf","text":"1"},{"marks":[{"data":{"book":"Joh","chapter":"20","verse":"1"},"object":"mark","type":"reference"}],"object":"leaf","text":"Now on the first day of the week, Mary Magdalene went early, while it was still dark, to the tomb, and saw the stone taken away from the tomb. "},{"marks":[{"data":{"book":"Joh","chapter":"20","verse":"2"},"object":"mark","type":"reference"},{"object":"mark","type":"verse"}],"object":"leaf","text":"2"},{"marks":[{"data":{"book":"Joh","chapter":"20","verse":"2"},"object":"mark","type":"reference"}],"object":"leaf","text":"Therefore she ran and came to Simon Peter, and to the other disciple whom Jesus loved, and said to them, "}]}]},{"data":{"color":"blue","recipient":"Simon Peter & John the Disciple","source":"Mary Magdalene","time_period":["0s AD"],"unique_recipients":["Simon Peter","John the Disciple"],"unique_sources":["Mary Magdalene"]},"nodes":[{"type":"prose","nodes":[{"marks":[{"data":{"book":"Joh","chapter":"20","verse":"2"},"object":"mark","type":"reference"}],"object":"leaf","text":"“They have taken away the Lord out of the tomb, and we don’t know where they have laid him!” "}]}]},{"data":{"color":"black","source":"The Narrator","time_period":["0s AD"],"unique_sources":["John the Disciple"]},"nodes":[{"type":"prose","nodes":[{"marks":[{"data":{"book":"Joh","chapter":"20","verse":"3"},"object":"mark","type":"reference"}],"object":"leaf","text":"\t"},{"marks":[{"data":{"book":"Joh","chapter":"20","verse":"3"},"object":"mark","type":"reference"},{"object":"mark","type":"verse"}],"object":"leaf","text":"3"},{"marks":[{"data":{"book":"Joh","chapter":"20","verse":"3"},"object":"mark","type":"reference"}],"object":"leaf","text":"Therefore Peter and the other disciple went out, and they went toward the tomb. "},{"marks":[{"data":{"book":"Joh","chapter":"20","verse":"4"},"object":"mark","type":"reference"},{"object":"mark","type":"verse"}],"object":"leaf","text":"4"},{"marks":[{"data":{"book":"Joh","chapter":"20","verse":"4"},"object":"mark","type":"reference"}],"object":"leaf","text":"They both ran together. The other disciple outran Peter, and came to the tomb first. "},{"marks":[{"data":{"book":"Joh","chapter":"20","verse":"5"},"object":"mark","type":"reference"},{"object":"mark","type":"verse"}],"object":"leaf","text":"5"},{"marks":[{"data":{"book":"Joh","chapter":"20","verse":"5"},"object":"mark","type":"reference"}],"object":"leaf","text":"Stooping and looking in, he saw the linen cloths lying, yet he didn’t enter in. "},{"marks":[{"data":{"book":"Joh","chapter":"20","verse":"6"},"object":"mark","type":"reference"},{"object":"mark","type":"verse"}],"object":"leaf","text":"6"},{"marks":[{"data":{"book":"Joh","chapter":"20","verse":"6"},"object":"mark","type":"reference"}],"object":"leaf","text":"Then Simon Peter came, following him, and entered into the tomb. He saw the linen cloths lying, "},{"marks":[{"data":{"book":"Joh","chapter":"20","verse":"7"},"object":"mark","type":"reference"},{"object":"mark","type":"verse"}],"object":"leaf","text":"7"},{"marks":[{"data":{"book":"Joh","chapter":"20","verse":"7"},"object":"mark","type":"reference"}],"object":"leaf","text":"and the cloth that had been on his head, not lying with the linen cloths, but rolled up in a place by itself. "},{"marks":[{"data":{"book":"Joh","chapter":"20","verse":"8"},"object":"mark","type":"reference"},{"object":"mark","type":"verse"}],"object":"leaf","text":"8"},{"marks":[{"data":{"book":"Joh","chapter":"20","verse":"8"},"object":"mark","type":"reference"}],"object":"leaf","text":"So then the other disciple who came first to the tomb also entered in, and he saw and believed. "},{"marks":[{"data":{"book":"Joh","chapter":"20","verse":"9"},"object":"mark","type":"reference"},{"object":"mark","type":"verse"}],"object":"leaf","text":"9"},{"marks":[{"data":{"book":"Joh","chapter":"20","verse":"9"},"object":"mark","type":"reference"}],"object":"leaf","text":"For as yet they didn’t know the Scripture, that he must rise from the dead. "},{"marks":[{"data":{"book":"Joh","chapter":"20","verse":"10"},"object":"mark","type":"reference"},{"object":"mark","type":"verse"}],"object":"leaf","text":"10"},{"marks":[{"data":{"book":"Joh","chapter":"20","verse":"10"},"object":"mark","type":"reference"}],"object":"leaf","text":"So the disciples went away again to their own homes. \n\t"},{"marks":[{"data":{"book":"Joh","chapter":"20","verse":"11"},"object":"mark","type":"reference"},{"object":"mark","type":"verse"}],"object":"leaf","text":"11"},{"marks":[{"data":{"book":"Joh","chapter":"20","verse":"11"},"object":"mark","type":"reference"}],"object":"leaf","text":"But Mary was standing outside at the tomb weeping. So, as she wept, she stooped and looked into the tomb, "},{"marks":[{"data":{"book":"Joh","chapter":"20","verse":"12"},"object":"mark","type":"reference"},{"object":"mark","type":"verse"}],"object":"leaf","text":"12"},{"marks":[{"data":{"book":"Joh","chapter":"20","verse":"12"},"object":"mark","type":"reference"}],"object":"leaf","text":"and she saw two angels in white sitting, one at the head, and one at the feet, where the body of Jesus had lain. "},{"marks":[{"data":{"book":"Joh","chapter":"20","verse":"13"},"object":"mark","type":"reference"},{"object":"mark","type":"verse"}],"object":"leaf","text":"13"},{"marks":[{"data":{"book":"Joh","chapter":"20","verse":"13"},"object":"mark","type":"reference"}],"object":"leaf","text":"They told her, "}]}]},{"data":{"color":"blue","recipient":"Mary Magdalene","source":"Two Angels","time_period":["0s AD"],"unique_recipients":["Mary Magdalene"],"unique_sources":["Two Angels"]},"nodes":[{"type":"prose","nodes":[{"marks":[{"data":{"book":"Joh","chapter":"20","verse":"13"},"object":"mark","type":"reference"}],"object":"leaf","text":"“Woman, why are you weeping?” "}]}]},{"data":{"color":"black","source":"The Narrator","time_period":["0s AD"],"unique_sources":["John the Disciple"]},"nodes":[{"type":"prose","nodes":[{"marks":[{"data":{"book":"Joh","chapter":"20","verse":"13"},"object":"mark","type":"reference"}],"object":"leaf","text":"\tShe said to them, "}]}]},{"data":{"color":"blue","recipient":"Two Angels","source":"Mary Magdalene","time_period":["0s AD"],"unique_recipients":["Two Angels"],"unique_sources":["Mary Magdalene"]},"nodes":[{"type":"prose","nodes":[{"marks":[{"data":{"book":"Joh","chapter":"20","verse":"13"},"object":"mark","type":"reference"}],"object":"leaf","text":"“Because they have taken away my Lord, and I don’t know where they have laid him.” "}]}]},{"data":{"color":"black","source":"The Narrator","time_period":["0s AD"],"unique_sources":["John the Disciple"]},"nodes":[{"type":"prose","nodes":[{"marks":[{"data":{"book":"Joh","chapter":"20","verse":"14"},"object":"mark","type":"reference"},{"object":"mark","type":"verse"}],"object":"leaf","text":"14"},{"marks":[{"data":{"book":"Joh","chapter":"20","verse":"14"},"object":"mark","type":"reference"}],"object":"leaf","text":"When she had said this, she turned around and saw Jesus standing, and didn’t know that it was Jesus. \n\t"},{"marks":[{"data":{"book":"Joh","chapter":"20","verse":"15"},"object":"mark","type":"reference"},{"object":"mark","type":"verse"}],"object":"leaf","text":"15"},{"marks":[{"data":{"book":"Joh","chapter":"20","verse":"15"},"object":"mark","type":"reference"}],"object":"leaf","text":"Jesus said to her, "}]}]},{"data":{"color":"red","recipient":"Mary Magdalene","source":"Jesus","time_period":["0s AD"],"unique_recipients":["Mary Magdalene"],"unique_sources":["Jesus"]},"nodes":[{"type":"prose","nodes":[{"marks":[{"data":{"book":"Joh","chapter":"20","verse":"15"},"object":"mark","type":"reference"}],"object":"leaf","text":"“Woman, why are you weeping? Who are you looking for?” "}]}]},{"data":{"color":"black","source":"The Narrator","time_period":["0s AD"],"unique_sources":["John the Disciple"]},"nodes":[{"type":"prose","nodes":[{"marks":[{"data":{"book":"Joh","chapter":"20","verse":"15"},"object":"mark","type":"reference"}],"object":"leaf","text":"\tShe, supposing him to be the gardener, said to him, "}]}]},{"data":{"color":"blue","recipient":"Jesus","source":"Mary Magdalene","time_period":["0s AD"],"unique_recipients":["Jesus"],"unique_sources":["Mary Magdalene"]},"nodes":[{"type":"prose","nodes":[{"marks":[{"data":{"book":"Joh","chapter":"20","verse":"15"},"object":"mark","type":"reference"}],"object":"leaf","text":"“Sir, if you have carried him away, tell me where you have laid him, and I will take him away.” "}]}]},{"data":{"color":"black","source":"The Narrator","time_period":["0s AD"],"unique_sources":["John the Disciple"]},"nodes":[{"type":"prose","nodes":[{"marks":[{"data":{"book":"Joh","chapter":"20","verse":"16"},"object":"mark","type":"reference"}],"object":"leaf","text":"\t"},{"marks":[{"data":{"book":"Joh","chapter":"20","verse":"16"},"object":"mark","type":"reference"},{"object":"mark","type":"verse"}],"object":"leaf","text":"16"},{"marks":[{"data":{"book":"Joh","chapter":"20","verse":"16"},"object":"mark","type":"reference"}],"object":"leaf","text":"Jesus said to her, "}]}]},{"data":{"color":"red","recipient":"Mary Magdalene","source":"Jesus","time_period":["0s AD"],"unique_recipients":["Mary Magdalene"],"unique_sources":["Jesus"]},"nodes":[{"type":"prose","nodes":[{"marks":[{"data":{"book":"Joh","chapter":"20","verse":"16"},"object":"mark","type":"reference"}],"object":"leaf","text":"“Mary.” "}]}]},{"data":{"color":"black","source":"The Narrator","time_period":["0s AD"],"unique_sources":["John the Disciple"]},"nodes":[{"type":"prose","nodes":[{"marks":[{"data":{"book":"Joh","chapter":"20","verse":"16"},"object":"mark","type":"reference"}],"object":"leaf","text":"\tShe turned and said to him, "}]}]},{"data":{"color":"blue","recipient":"Jesus","source":"Mary Magdalene","time_period":["0s AD"],"unique_recipients":["Jesus"],"unique_sources":["Mary Magdalene"]},"nodes":[{"type":"prose","nodes":[{"marks":[{"data":{"book":"Joh","chapter":"20","verse":"16"},"object":"mark","type":"reference"}],"object":"leaf","text":"“Rabboni!” "}]}]},{"data":{"color":"black","source":"The Narrator","time_period":["0s AD"],"unique_sources":["John the Disciple"]},"nodes":[{"type":"prose","nodes":[{"marks":[{"data":{"book":"Joh","chapter":"20","verse":"16"},"object":"mark","type":"reference"}],"object":"leaf","text":"which is to say, “Teacher!” \n\t"},{"marks":[{"data":{"book":"Joh","chapter":"20","verse":"17"},"object":"mark","type":"reference"},{"object":"mark","type":"verse"}],"object":"leaf","text":"17"},{"marks":[{"data":{"book":"Joh","chapter":"20","verse":"17"},"object":"mark","type":"reference"}],"object":"leaf","text":"Jesus said to her, "}]}]},{"data":{"color":"red","recipient":"Mary Magdalene","source":"Jesus","time_period":["0s AD"],"unique_recipients":["Mary Magdalene"],"unique_sources":["Jesus"]},"nodes":[{"type":"prose","nodes":[{"marks":[{"data":{"book":"Joh","chapter":"20","verse":"17"},"object":"mark","type":"reference"}],"object":"leaf","text":"“Don’t hold me, for I haven’t yet ascended to my Father; but go to my brothers, and tell them, ‘I am ascending to my Father and your Father, to my God and your God.’” "}]}]},{"data":{"color":"black","source":"The Narrator","time_period":["0s AD"],"unique_sources":["John the Disciple"]},"nodes":[{"type":"prose","nodes":[{"marks":[{"data":{"book":"Joh","chapter":"20","verse":"18"},"object":"mark","type":"reference"}],"object":"leaf","text":"\t"},{"marks":[{"data":{"book":"Joh","chapter":"20","verse":"18"},"object":"mark","type":"reference"},{"object":"mark","type":"verse"}],"object":"leaf","text":"18"},{"marks":[{"data":{"book":"Joh","chapter":"20","verse":"18"},"object":"mark","type":"reference"}],"object":"leaf","text":"Mary Magdalene came and told the disciples that she had seen the Lord, and that he had said these things to her. "},{"marks":[{"data":{"book":"Joh","chapter":"20","verse":"19"},"object":"mark","type":"reference"},{"object":"mark","type":"verse"}],"object":"leaf","text":"19"},{"marks":[{"data":{"book":"Joh","chapter":"20","verse":"19"},"object":"mark","type":"reference"}],"object":"leaf","text":"When therefore it was evening, on that day, the first day of the week, and when the doors were locked where the disciples were assembled, for fear of the Jews, Jesus came and stood in the middle, and said to them, "}]}]},{"data":{"color":"red","recipient":"Ten Disciples","source":"Jesus","time_period":["0s AD"],"unique_recipients":["Ten Disciples"],"unique_sources":["Jesus"]},"nodes":[{"type":"prose","nodes":[{"marks":[{"data":{"book":"Joh","chapter":"20","verse":"19"},"object":"mark","type":"reference"}],"object":"leaf","text":"“Peace be to you.” "}]}]},{"data":{"color":"black","source":"The Narrator","time_period":["0s AD"],"unique_sources":["John the Disciple"]},"nodes":[{"type":"prose","nodes":[{"marks":[{"data":{"book":"Joh","chapter":"20","verse":"20"},"object":"mark","type":"reference"}],"object":"leaf","text":"\t"},{"marks":[{"data":{"book":"Joh","chapter":"20","verse":"20"},"object":"mark","type":"reference"},{"object":"mark","type":"verse"}],"object":"leaf","text":"20"},{"marks":[{"data":{"book":"Joh","chapter":"20","verse":"20"},"object":"mark","type":"reference"}],"object":"leaf","text":"When he had said this, he showed them his hands and his side. The disciples therefore were glad when they saw the Lord. "},{"marks":[{"data":{"book":"Joh","chapter":"20","verse":"21"},"object":"mark","type":"reference"},{"object":"mark","type":"verse"}],"object":"leaf","text":"21"},{"marks":[{"data":{"book":"Joh","chapter":"20","verse":"21"},"object":"mark","type":"reference"}],"object":"leaf","text":"Jesus therefore said to them again, "}]}]},{"data":{"color":"red","recipient":"Ten Disciples","source":"Jesus","time_period":["0s AD"],"unique_recipients":["Ten Disciples"],"unique_sources":["Jesus"]},"nodes":[{"type":"prose","nodes":[{"marks":[{"data":{"book":"Joh","chapter":"20","verse":"21"},"object":"mark","type":"reference"}],"object":"leaf","text":"“Peace be to you. As the Father has sent me, even so I send you.” "}]}]},{"data":{"color":"black","source":"The Narrator","time_period":["0s AD"],"unique_sources":["John the Disciple"]},"nodes":[{"type":"prose","nodes":[{"marks":[{"data":{"book":"Joh","chapter":"20","verse":"22"},"object":"mark","type":"reference"},{"object":"mark","type":"verse"}],"object":"leaf","text":"22"},{"marks":[{"data":{"book":"Joh","chapter":"20","verse":"22"},"object":"mark","type":"reference"}],"object":"leaf","text":"When he had said this, he breathed on them, and said to them, "}]}]},{"data":{"color":"red","recipient":"Ten Disciples","source":"Jesus","time_period":["0s AD"],"unique_recipients":["Ten Disciples"],"unique_sources":["Jesus"]},"nodes":[{"type":"prose","nodes":[{"marks":[{"data":{"book":"Joh","chapter":"20","verse":"22"},"object":"mark","type":"reference"}],"object":"leaf","text":"“Receive the Holy Spirit! "},{"marks":[{"data":{"book":"Joh","chapter":"20","verse":"23"},"object":"mark","type":"reference"},{"object":"mark","type":"verse"}],"object":"leaf","text":"23"},{"marks":[{"data":{"book":"Joh","chapter":"20","verse":"23"},"object":"mark","type":"reference"}],"object":"leaf","text":"If you forgive anyone’s sins, they have been forgiven them. If you retain anyone’s sins, they have been retained.” "}]}]},{"data":{"color":"black","source":"The Narrator","time_period":["0s AD"],"unique_sources":["John the Disciple"]},"nodes":[{"type":"prose","nodes":[{"marks":[{"data":{"book":"Joh","chapter":"20","verse":"24"},"object":"mark","type":"reference"},{"object":"mark","type":"verse"}],"object":"leaf","text":"24"},{"marks":[{"data":{"book":"Joh","chapter":"20","verse":"24"},"object":"mark","type":"reference"}],"object":"leaf","text":"But Thomas, one of the twelve, called Didymus, wasn’t with them when Jesus came. "},{"marks":[{"data":{"book":"Joh","chapter":"20","verse":"25"},"object":"mark","type":"reference"},{"object":"mark","type":"verse"}],"object":"leaf","text":"25"},{"marks":[{"data":{"book":"Joh","chapter":"20","verse":"25"},"object":"mark","type":"reference"}],"object":"leaf","text":"The other disciples therefore said to him, "}]}]},{"data":{"color":"green","recipient":"Thomas","source":"Ten Disciples","time_period":["0s AD"],"unique_recipients":["Thomas"],"unique_sources":["Ten Disciples"]},"nodes":[{"type":"prose","nodes":[{"marks":[{"data":{"book":"Joh","chapter":"20","verse":"25"},"object":"mark","type":"reference"}],"object":"leaf","text":"“We have seen the Lord!” "}]}]},{"data":{"color":"black","source":"The Narrator","time_period":["0s AD"],"unique_sources":["John the Disciple"]},"nodes":[{"type":"prose","nodes":[{"marks":[{"data":{"book":"Joh","chapter":"20","verse":"25"},"object":"mark","type":"reference"}],"object":"leaf","text":"\tBut he said to them, "}]}]},{"data":{"color":"green","recipient":"Ten Disciples","source":"Thomas","time_period":["0s AD"],"unique_recipients":["Ten Disciples"],"unique_sources":["Thomas"]},"nodes":[{"type":"prose","nodes":[{"marks":[{"data":{"book":"Joh","chapter":"20","verse":"25"},"object":"mark","type":"reference"}],"object":"leaf","text":"“Unless I see in his hands the print of the nails, and put my hand into his side, I will not believe.” "}]}]},{"data":{"color":"black","source":"The Narrator","time_period":["0s AD"],"unique_sources":["John the Disciple"]},"nodes":[{"type":"prose","nodes":[{"marks":[{"data":{"book":"Joh","chapter":"20","verse":"26"},"object":"mark","type":"reference"}],"object":"leaf","text":"\t"},{"marks":[{"data":{"book":"Joh","chapter":"20","verse":"26"},"object":"mark","type":"reference"},{"object":"mark","type":"verse"}],"object":"leaf","text":"26"},{"marks":[{"data":{"book":"Joh","chapter":"20","verse":"26"},"object":"mark","type":"reference"}],"object":"leaf","text":"After eight days again his disciples were inside, and Thomas was with them. Jesus came, the doors being locked, and stood in the middle, and said, "}]}]},{"data":{"color":"red","recipient":"Eleven Disciples","source":"Jesus","time_period":["0s AD"],"unique_recipients":["Eleven Disciples"],"unique_sources":["Jesus"]},"nodes":[{"type":"prose","nodes":[{"marks":[{"data":{"book":"Joh","chapter":"20","verse":"26"},"object":"mark","type":"reference"}],"object":"leaf","text":"“Peace be to you.” "}]}]},{"data":{"color":"black","source":"The Narrator","time_period":["0s AD"],"unique_sources":["John the Disciple"]},"nodes":[{"type":"prose","nodes":[{"marks":[{"data":{"book":"Joh","chapter":"20","verse":"27"},"object":"mark","type":"reference"},{"object":"mark","type":"verse"}],"object":"leaf","text":"27"},{"marks":[{"data":{"book":"Joh","chapter":"20","verse":"27"},"object":"mark","type":"reference"}],"object":"leaf","text":"Then he said to Thomas, "}]}]},{"data":{"color":"red","recipient":"Thomas","source":"Jesus","time_period":["0s AD"],"unique_recipients":["Thomas"],"unique_sources":["Jesus"]},"nodes":[{"type":"prose","nodes":[{"marks":[{"data":{"book":"Joh","chapter":"20","verse":"27"},"object":"mark","type":"reference"}],"object":"leaf","text":"“Reach here your finger, and see my hands. Reach here your hand, and put it into my side. Don’t be unbelieving, but believing.” "}]}]},{"data":{"color":"black","source":"The Narrator","time_period":["0s AD"],"unique_sources":["John the Disciple"]},"nodes":[{"type":"prose","nodes":[{"marks":[{"data":{"book":"Joh","chapter":"20","verse":"28"},"object":"mark","type":"reference"}],"object":"leaf","text":"\t"},{"marks":[{"data":{"book":"Joh","chapter":"20","verse":"28"},"object":"mark","type":"reference"},{"object":"mark","type":"verse"}],"object":"leaf","text":"28"},{"marks":[{"data":{"book":"Joh","chapter":"20","verse":"28"},"object":"mark","type":"reference"}],"object":"leaf","text":"Thomas answered him, "}]}]},{"data":{"color":"green","recipient":"Jesus","source":"Thomas","time_period":["0s AD"],"unique_recipients":["Jesus"],"unique_sources":["Thomas"]},"nodes":[{"type":"prose","nodes":[{"marks":[{"data":{"book":"Joh","chapter":"20","verse":"28"},"object":"mark","type":"reference"}],"object":"leaf","text":"“My Lord and my God!” "}]}]},{"data":{"color":"black","source":"The Narrator","time_period":["0s AD"],"unique_sources":["John the Disciple"]},"nodes":[{"type":"prose","nodes":[{"marks":[{"data":{"book":"Joh","chapter":"20","verse":"29"},"object":"mark","type":"reference"}],"object":"leaf","text":"\t"},{"marks":[{"data":{"book":"Joh","chapter":"20","verse":"29"},"object":"mark","type":"reference"},{"object":"mark","type":"verse"}],"object":"leaf","text":"29"},{"marks":[{"data":{"book":"Joh","chapter":"20","verse":"29"},"object":"mark","type":"reference"}],"object":"leaf","text":"Jesus said to him, "}]}]},{"data":{"color":"red","recipient":"Thomas","source":"Jesus","time_period":["0s AD"],"unique_recipients":["Thomas"],"unique_sources":["Jesus"]},"nodes":[{"type":"prose","nodes":[{"marks":[{"data":{"book":"Joh","chapter":"20","verse":"29"},"object":"mark","type":"reference"}],"object":"leaf","text":"“Because you have seen me, you have believed. Blessed are those who have not seen, and have believed.” "}]}]},{"data":{"color":"black","source":"The Narrator","time_period":["0s AD"],"unique_sources":["John the Disciple"]},"nodes":[{"type":"prose","nodes":[{"marks":[{"data":{"book":"Joh","chapter":"20","verse":"30"},"object":"mark","type":"reference"}],"object":"leaf","text":"\t"},{"marks":[{"data":{"book":"Joh","chapter":"20","verse":"30"},"object":"mark","type":"reference"},{"object":"mark","type":"verse"}],"object":"leaf","text":"30"},{"marks":[{"data":{"book":"Joh","chapter":"20","verse":"30"},"object":"mark","type":"reference"}],"object":"leaf","text":"Therefore Jesus did many other signs in the presence of his disciples, which are not written in this book; "},{"marks":[{"data":{"book":"Joh","chapter":"20","verse":"31"},"object":"mark","type":"reference"},{"object":"mark","type":"verse"}],"object":"leaf","text":"31"},{"marks":[{"data":{"book":"Joh","chapter":"20","verse":"31"},"object":"mark","type":"reference"}],"object":"leaf","text":"but these are written, that you may believe that Jesus is the Christ, the Son of God, and that believing you may have life in his name. "},{"marks":[{"data":{"book":"Joh","chapter":"21","verse":"1"},"object":"mark","type":"reference"}],"object":"leaf","text":"\n\t"},{"marks":[{"data":{"book":"Joh","chapter":"21","verse":"1"},"object":"mark","type":"reference"},{"object":"mark","type":"chapter"}],"object":"leaf","text":"21"},{"marks":[{"data":{"book":"Joh","chapter":"21","verse":"1"},"object":"mark","type":"reference"},{"object":"mark","type":"verse"}],"object":"leaf","text":"1"},{"marks":[{"data":{"book":"Joh","chapter":"21","verse":"1"},"object":"mark","type":"reference"}],"object":"leaf","text":"After these things, Jesus revealed himself again to the disciples at the sea of Tiberias. He revealed himself this way. "},{"marks":[{"data":{"book":"Joh","chapter":"21","verse":"2"},"object":"mark","type":"reference"},{"object":"mark","type":"verse"}],"object":"leaf","text":"2"},{"marks":[{"data":{"book":"Joh","chapter":"21","verse":"2"},"object":"mark","type":"reference"}],"object":"leaf","text":"Simon Peter, Thomas called Didymus, Nathanael of Cana in Galilee, and the sons of Zebedee, and two others of his disciples were together. "},{"marks":[{"data":{"book":"Joh","chapter":"21","verse":"3"},"object":"mark","type":"reference"},{"object":"mark","type":"verse"}],"object":"leaf","text":"3"},{"marks":[{"data":{"book":"Joh","chapter":"21","verse":"3"},"object":"mark","type":"reference"}],"object":"leaf","text":"Simon Peter said to them, "}]}]},{"data":{"color":"green","recipient":"Six Disciples","source":"Simon Peter","time_period":["0s AD"],"unique_recipients":["Six Disciples"],"unique_sources":["Simon Peter"]},"nodes":[{"type":"prose","nodes":[{"marks":[{"data":{"book":"Joh","chapter":"21","verse":"3"},"object":"mark","type":"reference"}],"object":"leaf","text":"“I’m going fishing.” "}]}]},{"data":{"color":"black","source":"The Narrator","time_period":["0s AD"],"unique_sources":["John the Disciple"]},"nodes":[{"type":"prose","nodes":[{"marks":[{"data":{"book":"Joh","chapter":"21","verse":"3"},"object":"mark","type":"reference"}],"object":"leaf","text":"\tThey told him, "}]}]},{"data":{"color":"green","recipient":"Simon Peter","source":"Six Disciples","time_period":["0s AD"],"unique_recipients":["Simon Peter"],"unique_sources":["Six Disciples"]},"nodes":[{"type":"prose","nodes":[{"marks":[{"data":{"book":"Joh","chapter":"21","verse":"3"},"object":"mark","type":"reference"}],"object":"leaf","text":"“We are also coming with you.” "}]}]},{"data":{"color":"black","source":"The Narrator","time_period":["0s AD"],"unique_sources":["John the Disciple"]},"nodes":[{"type":"prose","nodes":[{"marks":[{"data":{"book":"Joh","chapter":"21","verse":"3"},"object":"mark","type":"reference"}],"object":"leaf","text":"They immediately went out, and entered into the boat. That night, they caught nothing. "},{"marks":[{"data":{"book":"Joh","chapter":"21","verse":"4"},"object":"mark","type":"reference"},{"object":"mark","type":"verse"}],"object":"leaf","text":"4"},{"marks":[{"data":{"book":"Joh","chapter":"21","verse":"4"},"object":"mark","type":"reference"}],"object":"leaf","text":"But when day had already come, Jesus stood on the beach, yet the disciples didn’t know that it was Jesus. "},{"marks":[{"data":{"book":"Joh","chapter":"21","verse":"5"},"object":"mark","type":"reference"},{"object":"mark","type":"verse"}],"object":"leaf","text":"5"},{"marks":[{"data":{"book":"Joh","chapter":"21","verse":"5"},"object":"mark","type":"reference"}],"object":"leaf","text":"Jesus therefore said to them, "}]}]},{"data":{"color":"red","recipient":"Seven Disciples","source":"Jesus","time_period":["0s AD"],"unique_recipients":["Seven Disciples"],"unique_sources":["Jesus"]},"nodes":[{"type":"prose","nodes":[{"marks":[{"data":{"book":"Joh","chapter":"21","verse":"5"},"object":"mark","type":"reference"}],"object":"leaf","text":"“Children, have you anything to eat?” "}]}]},{"data":{"color":"black","source":"The Narrator","time_period":["0s AD"],"unique_sources":["John the Disciple"]},"nodes":[{"type":"prose","nodes":[{"marks":[{"data":{"book":"Joh","chapter":"21","verse":"5"},"object":"mark","type":"reference"}],"object":"leaf","text":"\tThey answered him, "}]}]},{"data":{"color":"green","recipient":"Jesus","source":"Seven Disciples","time_period":["0s AD"],"unique_recipients":["Jesus"],"unique_sources":["Seven Disciples"]},"nodes":[{"type":"prose","nodes":[{"marks":[{"data":{"book":"Joh","chapter":"21","verse":"5"},"object":"mark","type":"reference"}],"object":"leaf","text":"“No.” "}]}]},{"data":{"color":"black","source":"The Narrator","time_period":["0s AD"],"unique_sources":["John the Disciple"]},"nodes":[{"type":"prose","nodes":[{"marks":[{"data":{"book":"Joh","chapter":"21","verse":"6"},"object":"mark","type":"reference"}],"object":"leaf","text":"\t"},{"marks":[{"data":{"book":"Joh","chapter":"21","verse":"6"},"object":"mark","type":"reference"},{"object":"mark","type":"verse"}],"object":"leaf","text":"6"},{"marks":[{"data":{"book":"Joh","chapter":"21","verse":"6"},"object":"mark","type":"reference"}],"object":"leaf","text":"He said to them, "}]}]},{"data":{"color":"red","recipient":"Seven Disciples","source":"Jesus","time_period":["0s AD"],"unique_recipients":["Seven Disciples"],"unique_sources":["Jesus"]},"nodes":[{"type":"prose","nodes":[{"marks":[{"data":{"book":"Joh","chapter":"21","verse":"6"},"object":"mark","type":"reference"}],"object":"leaf","text":"“Cast the net on the right side of the boat, and you will find some.” "}]}]},{"data":{"color":"black","source":"The Narrator","time_period":["0s AD"],"unique_sources":["John the Disciple"]},"nodes":[{"type":"prose","nodes":[{"marks":[{"data":{"book":"Joh","chapter":"21","verse":"6"},"object":"mark","type":"reference"}],"object":"leaf","text":"\tThey cast it therefore, and now they weren’t able to draw it in for the multitude of fish. "},{"marks":[{"data":{"book":"Joh","chapter":"21","verse":"7"},"object":"mark","type":"reference"},{"object":"mark","type":"verse"}],"object":"leaf","text":"7"},{"marks":[{"data":{"book":"Joh","chapter":"21","verse":"7"},"object":"mark","type":"reference"}],"object":"leaf","text":"That disciple therefore whom Jesus loved said to Peter, "}]}]},{"data":{"color":"green","recipient":"Simon Peter","source":"John the Disciple","time_period":["0s AD"],"unique_recipients":["Simon Peter"],"unique_sources":["John the Disciple"]},"nodes":[{"type":"prose","nodes":[{"marks":[{"data":{"book":"Joh","chapter":"21","verse":"7"},"object":"mark","type":"reference"}],"object":"leaf","text":"“It’s the Lord!” "}]}]},{"data":{"color":"black","source":"The Narrator","time_period":["0s AD"],"unique_sources":["John the Disciple"]},"nodes":[{"type":"prose","nodes":[{"marks":[{"data":{"book":"Joh","chapter":"21","verse":"7"},"object":"mark","type":"reference"}],"object":"leaf","text":"\tSo when Simon Peter heard that it was the Lord, he wrapped his coat around him (for he was naked), and threw himself into the sea. "},{"marks":[{"data":{"book":"Joh","chapter":"21","verse":"8"},"object":"mark","type":"reference"},{"object":"mark","type":"verse"}],"object":"leaf","text":"8"},{"marks":[{"data":{"book":"Joh","chapter":"21","verse":"8"},"object":"mark","type":"reference"}],"object":"leaf","text":"But the other disciples came in the little boat (for they were not far from the land, but about two hundred cubits away), dragging the net full of fish. "},{"marks":[{"data":{"book":"Joh","chapter":"21","verse":"9"},"object":"mark","type":"reference"},{"object":"mark","type":"verse"}],"object":"leaf","text":"9"},{"marks":[{"data":{"book":"Joh","chapter":"21","verse":"9"},"object":"mark","type":"reference"}],"object":"leaf","text":"So when they got out on the land, they saw a fire of coals there, and fish laid on it, and bread. "},{"marks":[{"data":{"book":"Joh","chapter":"21","verse":"10"},"object":"mark","type":"reference"},{"object":"mark","type":"verse"}],"object":"leaf","text":"10"},{"marks":[{"data":{"book":"Joh","chapter":"21","verse":"10"},"object":"mark","type":"reference"}],"object":"leaf","text":"Jesus said to them, "}]}]},{"data":{"color":"red","recipient":"Seven Disciples","source":"Jesus","time_period":["0s AD"],"unique_recipients":["Seven Disciples"],"unique_sources":["Jesus"]},"nodes":[{"type":"prose","nodes":[{"marks":[{"data":{"book":"Joh","chapter":"21","verse":"10"},"object":"mark","type":"reference"}],"object":"leaf","text":"“Bring some of the fish which you have just caught.” "}]}]},{"data":{"color":"black","source":"The Narrator","time_period":["0s AD"],"unique_sources":["John the Disciple"]},"nodes":[{"type":"prose","nodes":[{"marks":[{"data":{"book":"Joh","chapter":"21","verse":"11"},"object":"mark","type":"reference"}],"object":"leaf","text":"\t"},{"marks":[{"data":{"book":"Joh","chapter":"21","verse":"11"},"object":"mark","type":"reference"},{"object":"mark","type":"verse"}],"object":"leaf","text":"11"},{"marks":[{"data":{"book":"Joh","chapter":"21","verse":"11"},"object":"mark","type":"reference"}],"object":"leaf","text":"Simon Peter went up, and drew the net to land, full of great fish, one hundred fifty-three; and even though there were so many, the net wasn’t torn. \n\t"},{"marks":[{"data":{"book":"Joh","chapter":"21","verse":"12"},"object":"mark","type":"reference"},{"object":"mark","type":"verse"}],"object":"leaf","text":"12"},{"marks":[{"data":{"book":"Joh","chapter":"21","verse":"12"},"object":"mark","type":"reference"}],"object":"leaf","text":"Jesus said to them, "}]}]},{"data":{"color":"red","recipient":"Seven Disciples","source":"Jesus","time_period":["0s AD"],"unique_recipients":["Seven Disciples"],"unique_sources":["Jesus"]},"nodes":[{"type":"prose","nodes":[{"marks":[{"data":{"book":"Joh","chapter":"21","verse":"12"},"object":"mark","type":"reference"}],"object":"leaf","text":"“Come and eat breakfast.” "}]}]},{"data":{"color":"black","source":"The Narrator","time_period":["0s AD"],"unique_sources":["John the Disciple"]},"nodes":[{"type":"prose","nodes":[{"marks":[{"data":{"book":"Joh","chapter":"21","verse":"12"},"object":"mark","type":"reference"}],"object":"leaf","text":"\tNone of the disciples dared inquire of him, “Who are you?” knowing that it was the Lord. \n\t"},{"marks":[{"data":{"book":"Joh","chapter":"21","verse":"13"},"object":"mark","type":"reference"},{"object":"mark","type":"verse"}],"object":"leaf","text":"13"},{"marks":[{"data":{"book":"Joh","chapter":"21","verse":"13"},"object":"mark","type":"reference"}],"object":"leaf","text":"Then Jesus came and took the bread, gave it to them, and the fish likewise. "},{"marks":[{"data":{"book":"Joh","chapter":"21","verse":"14"},"object":"mark","type":"reference"},{"object":"mark","type":"verse"}],"object":"leaf","text":"14"},{"marks":[{"data":{"book":"Joh","chapter":"21","verse":"14"},"object":"mark","type":"reference"}],"object":"leaf","text":"This is now the third time that Jesus was revealed to his disciples, after he had risen from the dead. "},{"marks":[{"data":{"book":"Joh","chapter":"21","verse":"15"},"object":"mark","type":"reference"},{"object":"mark","type":"verse"}],"object":"leaf","text":"15"},{"marks":[{"data":{"book":"Joh","chapter":"21","verse":"15"},"object":"mark","type":"reference"}],"object":"leaf","text":"So when they had eaten their breakfast, Jesus said to Simon Peter, "}]}]},{"data":{"color":"red","recipient":"Simon Peter","source":"Jesus","time_period":["0s AD"],"unique_recipients":["Simon Peter"],"unique_sources":["Jesus"]},"nodes":[{"type":"prose","nodes":[{"marks":[{"data":{"book":"Joh","chapter":"21","verse":"15"},"object":"mark","type":"reference"}],"object":"leaf","text":"“Simon, son of Jonah, do you love me more than these?” "}]}]},{"data":{"color":"black","source":"The Narrator","time_period":["0s AD"],"unique_sources":["John the Disciple"]},"nodes":[{"type":"prose","nodes":[{"marks":[{"data":{"book":"Joh","chapter":"21","verse":"15"},"object":"mark","type":"reference"}],"object":"leaf","text":"\tHe said to him, "}]}]},{"data":{"color":"green","recipient":"Jesus","source":"Simon Peter","time_period":["0s AD"],"unique_recipients":["Jesus"],"unique_sources":["Simon Peter"]},"nodes":[{"type":"prose","nodes":[{"marks":[{"data":{"book":"Joh","chapter":"21","verse":"15"},"object":"mark","type":"reference"}],"object":"leaf","text":"“Yes, Lord; you know that I have affection for you.” "}]}]},{"data":{"color":"black","source":"The Narrator","time_period":["0s AD"],"unique_sources":["John the Disciple"]},"nodes":[{"type":"prose","nodes":[{"marks":[{"data":{"book":"Joh","chapter":"21","verse":"15"},"object":"mark","type":"reference"}],"object":"leaf","text":"\tHe said to him, "}]}]},{"data":{"color":"red","recipient":"Simon Peter","source":"Jesus","time_period":["0s AD"],"unique_recipients":["Simon Peter"],"unique_sources":["Jesus"]},"nodes":[{"type":"prose","nodes":[{"marks":[{"data":{"book":"Joh","chapter":"21","verse":"15"},"object":"mark","type":"reference"}],"object":"leaf","text":"“Feed my lambs.” "}]}]},{"data":{"color":"black","source":"The Narrator","time_period":["0s AD"],"unique_sources":["John the Disciple"]},"nodes":[{"type":"prose","nodes":[{"marks":[{"data":{"book":"Joh","chapter":"21","verse":"16"},"object":"mark","type":"reference"},{"object":"mark","type":"verse"}],"object":"leaf","text":"16"},{"marks":[{"data":{"book":"Joh","chapter":"21","verse":"16"},"object":"mark","type":"reference"}],"object":"leaf","text":"He said to him again a second time, "}]}]},{"data":{"color":"red","recipient":"Simon Peter","source":"Jesus","time_period":["0s AD"],"unique_recipients":["Simon Peter"],"unique_sources":["Jesus"]},"nodes":[{"type":"prose","nodes":[{"marks":[{"data":{"book":"Joh","chapter":"21","verse":"16"},"object":"mark","type":"reference"}],"object":"leaf","text":"“Simon, son of Jonah, do you love me?” "}]}]},{"data":{"color":"black","source":"The Narrator","time_period":["0s AD"],"unique_sources":["John the Disciple"]},"nodes":[{"type":"prose","nodes":[{"marks":[{"data":{"book":"Joh","chapter":"21","verse":"16"},"object":"mark","type":"reference"}],"object":"leaf","text":"\tHe said to him, "}]}]},{"data":{"color":"green","recipient":"Jesus","source":"Simon Peter","time_period":["0s AD"],"unique_recipients":["Jesus"],"unique_sources":["Simon Peter"]},"nodes":[{"type":"prose","nodes":[{"marks":[{"data":{"book":"Joh","chapter":"21","verse":"16"},"object":"mark","type":"reference"}],"object":"leaf","text":"“Yes, Lord; you know that I have affection for you.” "}]}]},{"data":{"color":"black","source":"The Narrator","time_period":["0s AD"],"unique_sources":["John the Disciple"]},"nodes":[{"type":"prose","nodes":[{"marks":[{"data":{"book":"Joh","chapter":"21","verse":"16"},"object":"mark","type":"reference"}],"object":"leaf","text":"\tHe said to him, "}]}]},{"data":{"color":"red","recipient":"Simon Peter","source":"Jesus","time_period":["0s AD"],"unique_recipients":["Simon Peter"],"unique_sources":["Jesus"]},"nodes":[{"type":"prose","nodes":[{"marks":[{"data":{"book":"Joh","chapter":"21","verse":"16"},"object":"mark","type":"reference"}],"object":"leaf","text":"“Tend my sheep.” "}]}]},{"data":{"color":"black","source":"The Narrator","time_period":["0s AD"],"unique_sources":["John the Disciple"]},"nodes":[{"type":"prose","nodes":[{"marks":[{"data":{"book":"Joh","chapter":"21","verse":"17"},"object":"mark","type":"reference"},{"object":"mark","type":"verse"}],"object":"leaf","text":"17"},{"marks":[{"data":{"book":"Joh","chapter":"21","verse":"17"},"object":"mark","type":"reference"}],"object":"leaf","text":"He said to him the third time, "}]}]},{"data":{"color":"red","recipient":"Simon Peter","source":"Jesus","time_period":["0s AD"],"unique_recipients":["Simon Peter"],"unique_sources":["Jesus"]},"nodes":[{"type":"prose","nodes":[{"marks":[{"data":{"book":"Joh","chapter":"21","verse":"17"},"object":"mark","type":"reference"}],"object":"leaf","text":"“Simon, son of Jonah, do you have affection for me?” "}]}]},{"data":{"color":"black","source":"The Narrator","time_period":["0s AD"],"unique_sources":["John the Disciple"]},"nodes":[{"type":"prose","nodes":[{"marks":[{"data":{"book":"Joh","chapter":"21","verse":"17"},"object":"mark","type":"reference"}],"object":"leaf","text":"\tPeter was grieved because he asked him the third time, “Do you have affection for me?” "},{"marks":[{"data":{"book":"Joh","chapter":"21","verse":"17"},"object":"mark","type":"reference"}],"object":"leaf","text":"He said to him, "}]}]},{"data":{"color":"green","recipient":"Jesus","source":"Simon Peter","time_period":["0s AD"],"unique_recipients":["Jesus"],"unique_sources":["Simon Peter"]},"nodes":[{"type":"prose","nodes":[{"marks":[{"data":{"book":"Joh","chapter":"21","verse":"17"},"object":"mark","type":"reference"}],"object":"leaf","text":"“Lord, you know everything. You know that I have affection for you.” "}]}]},{"data":{"color":"black","source":"The Narrator","time_period":["0s AD"],"unique_sources":["John the Disciple"]},"nodes":[{"type":"prose","nodes":[{"marks":[{"data":{"book":"Joh","chapter":"21","verse":"17"},"object":"mark","type":"reference"}],"object":"leaf","text":"\tJesus said to him, "}]}]},{"data":{"color":"red","recipient":"Simon Peter","source":"Jesus","time_period":["0s AD"],"unique_recipients":["Simon Peter"],"unique_sources":["Jesus"]},"nodes":[{"type":"prose","nodes":[{"marks":[{"data":{"book":"Joh","chapter":"21","verse":"17"},"object":"mark","type":"reference"}],"object":"leaf","text":"“Feed my sheep. "},{"marks":[{"data":{"book":"Joh","chapter":"21","verse":"18"},"object":"mark","type":"reference"},{"object":"mark","type":"verse"}],"object":"leaf","text":"18"},{"marks":[{"data":{"book":"Joh","chapter":"21","verse":"18"},"object":"mark","type":"reference"}],"object":"leaf","text":"Most certainly I tell you, when you were young, you dressed yourself, and walked where you wanted to. But when you are old, you will stretch out your hands, and another will dress you, and carry you where you don’t want to go.” "}]}]},{"data":{"color":"black","source":"The Narrator","time_period":["0s AD"],"unique_sources":["John the Disciple"]},"nodes":[{"type":"prose","nodes":[{"marks":[{"data":{"book":"Joh","chapter":"21","verse":"19"},"object":"mark","type":"reference"}],"object":"leaf","text":"\t"},{"marks":[{"data":{"book":"Joh","chapter":"21","verse":"19"},"object":"mark","type":"reference"},{"object":"mark","type":"verse"}],"object":"leaf","text":"19"},{"marks":[{"data":{"book":"Joh","chapter":"21","verse":"19"},"object":"mark","type":"reference"}],"object":"leaf","text":"Now he said this, signifying by what kind of death he would glorify God. When he had said this, he said to him, "}]}]},{"data":{"color":"red","recipient":"Simon Peter","source":"Jesus","time_period":["0s AD"],"unique_recipients":["Simon Peter"],"unique_sources":["Jesus"]},"nodes":[{"type":"prose","nodes":[{"marks":[{"data":{"book":"Joh","chapter":"21","verse":"19"},"object":"mark","type":"reference"}],"object":"leaf","text":"“Follow me.” "}]}]},{"data":{"color":"black","source":"The Narrator","time_period":["0s AD"],"unique_sources":["John the Disciple"]},"nodes":[{"type":"prose","nodes":[{"marks":[{"data":{"book":"Joh","chapter":"21","verse":"20"},"object":"mark","type":"reference"}],"object":"leaf","text":"\t"},{"marks":[{"data":{"book":"Joh","chapter":"21","verse":"20"},"object":"mark","type":"reference"},{"object":"mark","type":"verse"}],"object":"leaf","text":"20"},{"marks":[{"data":{"book":"Joh","chapter":"21","verse":"20"},"object":"mark","type":"reference"}],"object":"leaf","text":"Then Peter, turning around, saw a disciple following. This was the disciple whom Jesus loved, the one who had also leaned on Jesus’ breast at the supper and asked, “Lord, who is going to betray You?” "},{"marks":[{"data":{"book":"Joh","chapter":"21","verse":"21"},"object":"mark","type":"reference"},{"object":"mark","type":"verse"}],"object":"leaf","text":"21"},{"marks":[{"data":{"book":"Joh","chapter":"21","verse":"21"},"object":"mark","type":"reference"}],"object":"leaf","text":"Peter seeing him, said to Jesus, "}]}]},{"data":{"color":"green","recipient":"Jesus","source":"Simon Peter","time_period":["0s AD"],"unique_recipients":["Jesus"],"unique_sources":["Simon Peter"]},"nodes":[{"type":"prose","nodes":[{"marks":[{"data":{"book":"Joh","chapter":"21","verse":"21"},"object":"mark","type":"reference"}],"object":"leaf","text":"“Lord, what about this man?” "}]}]},{"data":{"color":"black","source":"The Narrator","time_period":["0s AD"],"unique_sources":["John the Disciple"]},"nodes":[{"type":"prose","nodes":[{"marks":[{"data":{"book":"Joh","chapter":"21","verse":"22"},"object":"mark","type":"reference"}],"object":"leaf","text":"\t"},{"marks":[{"data":{"book":"Joh","chapter":"21","verse":"22"},"object":"mark","type":"reference"},{"object":"mark","type":"verse"}],"object":"leaf","text":"22"},{"marks":[{"data":{"book":"Joh","chapter":"21","verse":"22"},"object":"mark","type":"reference"}],"object":"leaf","text":"Jesus said to him, "}]}]},{"data":{"color":"red","recipient":"Simon Peter","source":"Jesus","time_period":["0s AD"],"unique_recipients":["Simon Peter"],"unique_sources":["Jesus"]},"nodes":[{"type":"prose","nodes":[{"marks":[{"data":{"book":"Joh","chapter":"21","verse":"22"},"object":"mark","type":"reference"}],"object":"leaf","text":"“If I desire that he stay until I come, what is that to you? You follow me.” "}]}]},{"data":{"color":"black","source":"The Narrator","time_period":["0s AD"],"unique_sources":["John the Disciple"]},"nodes":[{"type":"prose","nodes":[{"marks":[{"data":{"book":"Joh","chapter":"21","verse":"23"},"object":"mark","type":"reference"},{"object":"mark","type":"verse"}],"object":"leaf","text":"23"},{"marks":[{"data":{"book":"Joh","chapter":"21","verse":"23"},"object":"mark","type":"reference"}],"object":"leaf","text":"This saying therefore went out among the brothers, that this disciple wouldn’t die. Yet Jesus didn’t say to him that he wouldn’t die, but, “If I desire that he stay until I come, what is that to you?” \n\t"},{"marks":[{"data":{"book":"Joh","chapter":"21","verse":"24"},"object":"mark","type":"reference"},{"object":"mark","type":"verse"}],"object":"leaf","text":"24"},{"marks":[{"data":{"book":"Joh","chapter":"21","verse":"24"},"object":"mark","type":"reference"}],"object":"leaf","text":"This is the disciple who testifies about these things, and wrote these things. We know that his witness is true. "},{"marks":[{"data":{"book":"Joh","chapter":"21","verse":"25"},"object":"mark","type":"reference"},{"object":"mark","type":"verse"}],"object":"leaf","text":"25"},{"marks":[{"data":{"book":"Joh","chapter":"21","verse":"25"},"object":"mark","type":"reference"}],"object":"leaf","text":"There are also many other things which Jesus did, which if they would all be written, I suppose that even the world itself wouldn’t have room for the books that would be written. "}]}]}],"colors":{"total":1422,"black":1012,"red":267,"green":82,"blue":61},"repeatedWords":["said (39)","have (22)","Jesus (30)","Lord (14)","disciples (13)","Peter (13)","had (12)","Simon (10)","came (10)","know (10)","me (10)","disciple (9)","tomb (9)","saw (9)","therefore (8)","other (8)","where (7)","away (7)","went (7)","fish (6)"],"sources":{"The Narrator":{"words":1012,"color":"black"},"Mary Magdalene":{"words":56,"color":"blue"},"Two Angels":{"words":5,"color":"blue"},"Jesus":{"words":267,"color":"red"},"Ten Disciples":{"words":5,"color":"green"},"Thomas":{"words":27,"color":"green"},"Simon Peter":{"words":40,"color":"green"},"Six Disciples":{"words":6,"color":"green"},"Seven Disciples":{"words":1,"color":"green"},"John the Disciple":{"words":3,"color":"green"}},"id":"S307"}